nnfabrik/__init__.py
nnfabrik/builder.py
nnfabrik/main.py
nnfabrik/examples/__init__.py
nnfabrik/examples/nnfabrik.py
nnfabrik/examples/mnist/__init__.py
nnfabrik/examples/mnist/dataset.py
nnfabrik/examples/mnist/model.py
nnfabrik/examples/mnist/trainer.py
nnfabrik/examples/mnist_checkpoint/__init__.py
nnfabrik/examples/mnist_checkpoint/trainer.py
nnfabrik/examples/mnist_transfer/__init__.py
nnfabrik/examples/mnist_transfer/dataset.py
nnfabrik/examples/mnist_transfer/trainer.py
nnfabrik/examples/notebooks/checkpoint_example.ipynb
nnfabrik/examples/notebooks/experiments_example.ipynb
nnfabrik/examples/notebooks/nnfabrik_example.ipynb
nnfabrik/examples/notebooks/transfer_example.ipynb
nnfabrik/templates/__init__.py
nnfabrik/templates/checkpoint.py
nnfabrik/templates/scoring.py
nnfabrik/templates/trained_model.py
nnfabrik/templates/utility.py
nnfabrik/templates/transfer/__init__.py
nnfabrik/templates/transfer/checkpoint.py
nnfabrik/templates/transfer/recipes.py
nnfabrik/templates/transfer/transferred_trained_model.py
nnfabrik/utility/__init__.py
nnfabrik/utility/dj_helpers.py
nnfabrik/utility/hypersearch.py
nnfabrik/utility/nn_helpers.py
nnfabrik/utility/nnf_helper.py
nnfabrik-0.2.1.dist-info/METADATA
nnfabrik-0.2.1.dist-info/WHEEL
nnfabrik-0.2.1.dist-info/top_level.txt
nnfabrik-0.2.1.dist-info/RECORD
